pyskylumos/__init__.py
pyskylumos/engine/Engine.py
pyskylumos/engine/__init__.py
pyskylumos/sensor/MicroPolarizer.py
pyskylumos/sensor/OpticalConjugator.py
pyskylumos/sensor/SensorChip.py
pyskylumos/sensor/SlicingPattern.py
pyskylumos/sensor/StokesCalculator.py
pyskylumos/sensor/__init__.py
pyskylumos/sky_models/Berry.py
pyskylumos/sky_models/Pan.py
pyskylumos/sky_models/Rayleigh.py
pyskylumos/sky_models/SkySimulator.py
pyskylumos/sky_models/__init__.py
pyskylumos-0.0.5.dist-info/METADATA
pyskylumos-0.0.5.dist-info/WHEEL
pyskylumos-0.0.5.dist-info/licenses/LICENSE
pyskylumos-0.0.5.dist-info/RECORD
